README.md
auth/__init__.py
auth/hmac_authenticated_client.py
examples/__init__.py
examples/hmac_authentication_example.py
blood_hound_api_client/__init__.py
blood_hound_api_client/api/__init__.py
blood_hound_api_client/api/ad_base_entities/__init__.py
blood_hound_api_client/api/ad_base_entities/get_entity.py
blood_hound_api_client/api/ad_base_entities/get_entity_controllables.py
blood_hound_api_client/api/ad_base_entities/get_entity_controllers.py
blood_hound_api_client/api/ad_users/__init__.py
blood_hound_api_client/api/ad_users/get_user_entity.py
blood_hound_api_client/api/ad_users/get_user_entity_admin_rights.py
blood_hound_api_client/api/ad_users/get_user_entity_constrained_delegation_rights.py
blood_hound_api_client/api/ad_users/get_user_entity_controllables.py
blood_hound_api_client/api/ad_users/get_user_entity_controllers.py
blood_hound_api_client/api/ad_users/get_user_entity_dcom_rights.py
blood_hound_api_client/api/ad_users/get_user_entity_membership.py
blood_hound_api_client/api/ad_users/get_user_entity_ps_remote_rights.py
blood_hound_api_client/api/ad_users/get_user_entity_rdp_rights.py
blood_hound_api_client/api/ad_users/get_user_entity_sessions.py
blood_hound_api_client/api/ad_users/get_user_entity_sql_admin_rights.py
blood_hound_api_client/api/aia_c_as/__init__.py
blood_hound_api_client/api/aia_c_as/get_aia_ca_entity.py
blood_hound_api_client/api/aia_c_as/get_aia_ca_entity_controllers.py
blood_hound_api_client/api/analysis/__init__.py
blood_hound_api_client/api/analysis/get_asset_group_combo_node.py
blood_hound_api_client/api/analysis/get_combo_tree_graph.py
blood_hound_api_client/api/analysis/get_latest_tier_zero_combo_node.py
blood_hound_api_client/api/api_info/__init__.py
blood_hound_api_client/api/api_info/get_api_spec.py
blood_hound_api_client/api/api_info/get_api_version.py
blood_hound_api_client/api/api_tokens/__init__.py
blood_hound_api_client/api/api_tokens/create_auth_token.py
blood_hound_api_client/api/api_tokens/delete_auth_token.py
blood_hound_python_client-2.0.0.dist-info/LICENSE
blood_hound_python_client-2.0.0.dist-info/METADATA
blood_hound_python_client-2.0.0.dist-info/WHEEL
blood_hound_python_client-2.0.0.dist-info/RECORD
