Metadata-Version: 2.1
Name: blood-hound-python-client
Version: 2.0.0
Summary: A client library for accessing BloodHound API
Home-page: https://github.com/SpecterOps/bloodhound-python-sdk
License: APACHE
Keywords: bloodhound,api,sdk,client
Author: SpecterOps
Author-email: info@specterops.io
Requires-Python: >=3.8,<4.0
Classifier: Development Status :: 4 - Beta
Classifier: Intended Audience :: Developers
Classifier: License :: Other/Proprietary License
Classifier: Programming Language :: Python :: 3
Classifier: Programming Language :: Python :: 3.8
Classifier: Programming Language :: Python :: 3.9
Classifier: Programming Language :: Python :: 3.10
Classifier: Programming Language :: Python :: 3.11
Classifier: Programming Language :: Python :: 3.12
Requires-Dist: attrs (>=21.3.0)
Requires-Dist: httpx (>=0.27,<0.28)
Requires-Dist: python-dateutil (>=2.8.0,<3.0.0)
Project-URL: Repository, https://github.com/SpecterOps/bloodhound-python-sdk
